README
setup.cfg
setup.py
graphagus/__init__.py
graphagus/core.py
graphagus/test.py
graphagus.egg-info/PKG-INFO
graphagus.egg-info/SOURCES.txt
graphagus.egg-info/dependency_links.txt
graphagus.egg-info/entry_points.txt
graphagus.egg-info/not-zip-safe
graphagus.egg-info/requires.txt
graphagus.egg-info/top_level.txt