Metadata-Version: 1.1
Name: graphagus
Version: 0.3dev
Summary: A graph database for property graphs on top of ZODB
Home-page: https://github.com/jhb/graphagus
Author: Joerg Baach
Author-email: mail@baach.de
License: GPL
Keywords: graph ZODB
Platform: UNKNOWN
Classifier: License :: OSI Approved :: GNU General Public License (GPL)
Classifier: Programming Language :: Python
Classifier: Development Status :: 3 - Alpha
Classifier: Intended Audience :: Developers
Classifier: Topic :: Database
